pdf_to_string_converter/__init__.py
pdf_to_string_converter-2025.9.13209.dist-info/licenses/LICENSE
pdf_to_string_converter-2025.9.13209.dist-info/METADATA
pdf_to_string_converter-2025.9.13209.dist-info/WHEEL
pdf_to_string_converter-2025.9.13209.dist-info/top_level.txt
pdf_to_string_converter-2025.9.13209.dist-info/RECORD
