Metadata-Version: 2.4
Name: pdf_to_string_converter
Version: 2025.9.13209
Summary: Convert pdf to plain string (multiline if needed)
Author-email: Eugene Evstafev <hi@eugene.plus>
License: MIT License
Project-URL: Repository, https://pypi.org/project/pdf_to_string_converter/
Requires-Python: >=3.9
License-File: LICENSE
Requires-Dist: pypdfium2
Requires-Dist: textract
Requires-Dist: tika
Requires-Dist: pdfplumber
Requires-Dist: pdftotext
Dynamic: license-file
